sqlnet_predict.py
sqlnet_predict-0.1.0.dist-info/LICENSE
sqlnet_predict-0.1.0.dist-info/METADATA
sqlnet_predict-0.1.0.dist-info/WHEEL
sqlnet_predict-0.1.0.dist-info/RECORD
