Metadata-Version: 2.1
Name: sqlnet-predict
Version: 0.1.0
Summary: This repo provides an implementation of SQLNet and Seq2SQL neural networks for predicting SQL queries on [WikiSQL dataset](https://github.com/salesforce/WikiSQL). The paper is available at [here](https://arxiv.org/abs/1711.04436).
License: BSD-3-Clause license
Author: Your Name
Author-email: you@example.com
Requires-Python: >=3.10,<4.0
Classifier: License :: Other/Proprietary License
Classifier: Programming Language :: Python :: 3
Classifier: Programming Language :: Python :: 3.10
Classifier: Programming Language :: Python :: 3.11
Requires-Dist: Babel (>=2.5.1,<3.0.0)
Requires-Dist: SQLAlchemy (>=1.1.14,<2.0.0)
Requires-Dist: docopt (>=0.6.2,<0.7.0)
Requires-Dist: et-xmlfile (>=1.0.1,<2.0.0)
Requires-Dist: jdcal (>=1.3,<2.0)
Requires-Dist: odfpy (>=1.3.5,<2.0.0)
Requires-Dist: openpyxl (>=2.4.9,<3.0.0)
Requires-Dist: pytz (>=2017.3,<2018.0)
Requires-Dist: records (>=0.5.2,<0.6.0)
Requires-Dist: tablib (>=0.12.1,<0.13.0)
Requires-Dist: unicodecsv (>=0.14.1,<0.15.0)
Requires-Dist: xlrd (>=1.1.0,<2.0.0)
Requires-Dist: xlwt (>=1.3.0,<2.0.0)
